{"commitInfo":{"timestamp":1782953070569,"operation":"STREAMING UPDATE","operationParameters":{"outputMode":"Append","queryId":"faf63cc1-6908-4eb3-a6f4-55fb4145de91","epochId":"456"},"readVersion":455,"isolationLevel":"Serializable","isBlindAppend":true,"operationMetrics":{"numRemovedFiles":"0","numOutputRows":"2","numOutputBytes":"2551","numAddedFiles":"1"},"engineInfo":"Apache-Spark/3.4.4 Delta-Lake/2.4.0","txnId":"11b7774a-d8b1-4e30-b23e-f3f6a15c2650"}}
{"txn":{"appId":"faf63cc1-6908-4eb3-a6f4-55fb4145de91","version":456,"lastUpdated":1782953070569}}
{"add":{"path":"part-00000-716700b8-38e2-44fa-be56-e004db14aac3-c000.snappy.parquet","partitionValues":{},"size":2551,"modificationTime":1782953070555,"dataChange":true,"stats":"{\"numRecords\":2,\"minValues\":{\"id\":4480,\"id_salarie\":73367,\"type_sport\":\"BOXE\",\"distance\":9626.0,\"date_debut\":\"1736727204000000\",\"date_fin\":\"1736733960000000\",\"commentaire\":\"Denise Lambert - TENNIS DE TABLE\",\"duration_sec\":2991},\"maxValues\":{\"id\":4481,\"id_salarie\":89328,\"type_sport\":\"TENNIS DE TABLE\",\"distance\":13648.0,\"date_debut\":\"1766742568000000\",\"date_fin\":\"1766745559000000\",\"commentaire\":\"Simon Verdier - BOXE\",\"duration_sec\":6756},\"nullCount\":{\"id\":0,\"id_salarie\":0,\"type_sport\":0,\"distance\":0,\"date_debut\":0,\"date_fin\":0,\"commentaire\":0,\"duration_sec\":0}}"}}
