{"commitInfo":{"timestamp":1782951598106,"operation":"STREAMING UPDATE","operationParameters":{"outputMode":"Append","queryId":"faf63cc1-6908-4eb3-a6f4-55fb4145de91","epochId":"230"},"readVersion":229,"isolationLevel":"Serializable","isBlindAppend":true,"operationMetrics":{"numRemovedFiles":"0","numOutputRows":"2","numOutputBytes":"2513","numAddedFiles":"1"},"engineInfo":"Apache-Spark/3.4.4 Delta-Lake/2.4.0","txnId":"6b51c39e-0b0d-4b26-a450-623deb69ea6b"}}
{"txn":{"appId":"faf63cc1-6908-4eb3-a6f4-55fb4145de91","version":230,"lastUpdated":1782951598094}}
{"add":{"path":"part-00000-b3514155-c632-4259-accd-235eef6f1ac0-c000.snappy.parquet","partitionValues":{},"size":2513,"modificationTime":1782951597859,"dataChange":true,"stats":"{\"numRecords\":2,\"minValues\":{\"id\":4086,\"id_salarie\":73367,\"type_sport\":\"BOXE\",\"distance\":5610.0,\"date_debut\":\"1743379613000000\",\"date_fin\":\"1743385550000000\",\"commentaire\":\"Claudine Joubert - FOOTBALL\",\"duration_sec\":5610},\"maxValues\":{\"id\":4087,\"id_salarie\":76341,\"type_sport\":\"FOOTBALL\",\"distance\":9243.0,\"date_debut\":\"1757116096000000\",\"date_fin\":\"1757121706000000\",\"commentaire\":\"Simon Verdier - BOXE\",\"duration_sec\":5937},\"nullCount\":{\"id\":0,\"id_salarie\":0,\"type_sport\":0,\"distance\":0,\"date_debut\":0,\"date_fin\":0,\"commentaire\":0,\"duration_sec\":0}}"}}
