{"commitInfo":{"timestamp":1782952489331,"operation":"STREAMING UPDATE","operationParameters":{"outputMode":"Append","queryId":"faf63cc1-6908-4eb3-a6f4-55fb4145de91","epochId":"358"},"readVersion":357,"isolationLevel":"Serializable","isBlindAppend":true,"operationMetrics":{"numRemovedFiles":"0","numOutputRows":"2","numOutputBytes":"2514","numAddedFiles":"1"},"engineInfo":"Apache-Spark/3.4.4 Delta-Lake/2.4.0","txnId":"42a5ca9b-0469-4a69-9bc4-a65d452df7a0"}}
{"txn":{"appId":"faf63cc1-6908-4eb3-a6f4-55fb4145de91","version":358,"lastUpdated":1782952489331}}
{"add":{"path":"part-00000-47db32db-8e2e-4663-a7cd-15ec67224f05-c000.snappy.parquet","partitionValues":{},"size":2514,"modificationTime":1782952489322,"dataChange":true,"stats":"{\"numRecords\":2,\"minValues\":{\"id\":4325,\"id_salarie\":17036,\"type_sport\":\"ESCALADE\",\"distance\":8360.0,\"date_debut\":\"1752762161000000\",\"date_fin\":\"1752764452000000\",\"commentaire\":\"Julien Jacques - ESCALADE\",\"duration_sec\":2161},\"maxValues\":{\"id\":4326,\"id_salarie\":53944,\"type_sport\":\"NATATION\",\"distance\":8588.0,\"date_debut\":\"1766651139000000\",\"date_fin\":\"1766653300000000\",\"commentaire\":\"Nath Lebon - NATATION\",\"duration_sec\":2291},\"nullCount\":{\"id\":0,\"id_salarie\":0,\"type_sport\":0,\"distance\":0,\"date_debut\":0,\"date_fin\":0,\"commentaire\":0,\"duration_sec\":0}}"}}
