{"commitInfo":{"timestamp":1782952730292,"operation":"STREAMING UPDATE","operationParameters":{"outputMode":"Append","queryId":"faf63cc1-6908-4eb3-a6f4-55fb4145de91","epochId":"398"},"readVersion":397,"isolationLevel":"Serializable","isBlindAppend":true,"operationMetrics":{"numRemovedFiles":"0","numOutputRows":"1","numOutputBytes":"2555","numAddedFiles":"1"},"engineInfo":"Apache-Spark/3.4.4 Delta-Lake/2.4.0","txnId":"199e6f39-1c9d-459b-8cfe-5bb51e7b6e17"}}
{"txn":{"appId":"faf63cc1-6908-4eb3-a6f4-55fb4145de91","version":398,"lastUpdated":1782952730292}}
{"add":{"path":"part-00000-56454993-6fd8-47af-ae49-2d03ffd17b06-c000.snappy.parquet","partitionValues":{},"size":2555,"modificationTime":1782952730284,"dataChange":true,"stats":"{\"numRecords\":1,\"minValues\":{\"id\":4391,\"id_salarie\":67121,\"type_sport\":\"RUGBY\",\"distance\":3807.0,\"date_debut\":\"1755726054000000\",\"date_fin\":\"1755728163000000\",\"commentaire\":\"Claudine Pasquier - RUGBY\",\"duration_sec\":2109},\"maxValues\":{\"id\":4391,\"id_salarie\":67121,\"type_sport\":\"RUGBY\",\"distance\":3807.0,\"date_debut\":\"1755726054000000\",\"date_fin\":\"1755728163000000\",\"commentaire\":\"Claudine Pasquier - RUGBY\",\"duration_sec\":2109},\"nullCount\":{\"id\":0,\"id_salarie\":0,\"type_sport\":0,\"distance\":0,\"date_debut\":0,\"date_fin\":0,\"commentaire\":0,\"duration_sec\":0}}"}}
